mini_tem/__init__.py
mini_tem/aperture.py
mini_tem/bipole.py
mini_tem/biprism.py
mini_tem/component.py
mini_tem/component_field.py
mini_tem/deflector.py
mini_tem/electron.py
mini_tem/electron_source.py
mini_tem/half_thick_lens.py
mini_tem/i2tem.json
mini_tem/i2tem.py
mini_tem/lens.py
mini_tem/main.qml
mini_tem/minitem.py
mini_tem/sample.py
mini_tem/shifter.py
mini_tem/stigmator.py
mini_tem/test.json
mini_tem/tilter.py
mini_tem/utils.py
mini_tem-2024.10.10.0.dist-info/METADATA
mini_tem-2024.10.10.0.dist-info/WHEEL
mini_tem-2024.10.10.0.dist-info/RECORD
