Metadata-Version: 2.1
Name: mini-tem
Version: 2024.10.10.0
Summary: Implementation of a 3D TEM simulation based on 
Home-page: https://github.com/I3EM/miniTEM
License: GPL-3.0
Keywords: TEM,simulation,3D
Author: Darknestea
Author-email: loic.grossetete@cemes.fr
Requires-Python: >=3.8,<3.12
Classifier: Development Status :: 3 - Alpha
Classifier: Intended Audience :: Developers
Classifier: License :: OSI Approved :: GNU General Public License v3 (GPLv3)
Classifier: Programming Language :: Python :: 3
Classifier: Programming Language :: Python :: 3.8
Classifier: Programming Language :: Python :: 3.9
Classifier: Programming Language :: Python :: 3.10
Classifier: Programming Language :: Python :: 3.11
Requires-Dist: matplotlib (>=3.7.2,<4.0.0)
Requires-Dist: numpy (>=1.24.2,<2.0.0)
Requires-Dist: pyside6 (>=6.4.3,<7.0.0)
Requires-Dist: scipy (>=1.7.1,<2.0.0)
Requires-Dist: seaborn (>=0.13.2,<0.14.0)
Project-URL: Repository, https://github.com/I3EM/miniTEM
